autosidebar/autosidebar.py
github_wiki_autosidebar-1.0.1.dist-info/LICENSE
github_wiki_autosidebar-1.0.1.dist-info/METADATA
github_wiki_autosidebar-1.0.1.dist-info/WHEEL
github_wiki_autosidebar-1.0.1.dist-info/entry_points.txt
github_wiki_autosidebar-1.0.1.dist-info/top_level.txt
github_wiki_autosidebar-1.0.1.dist-info/RECORD
