Metadata-Version: 2.1
Name: github-wiki-autosidebar
Version: 1.0.1
Summary: Simple utility to generate a sidebar for github wikis
Home-page: https://github.com/benrutter/github-wiki-autosidbar
Author: benrutter
License: UNKNOWN
Platform: UNKNOWN
License-File: LICENSE
